oorange/__init__.py
oorange/gift.py
oorange-0.1.dist-info/METADATA
oorange-0.1.dist-info/WHEEL
oorange-0.1.dist-info/top_level.txt
oorange-0.1.dist-info/RECORD
